streamlit_l7/__init__.py
streamlit_l7/frontend/build/asset-manifest.json
streamlit_l7/frontend/build/index.html
streamlit_l7/frontend/build/static/js/2.6c2d8050.chunk.js
streamlit_l7/frontend/build/static/js/2.6c2d8050.chunk.js.LICENSE.txt
streamlit_l7/frontend/build/static/js/2.6c2d8050.chunk.js.map
streamlit_l7/frontend/build/static/js/2.d71e5df1.chunk.js
streamlit_l7/frontend/build/static/js/2.d71e5df1.chunk.js.LICENSE.txt
streamlit_l7/frontend/build/static/js/2.d71e5df1.chunk.js.map
streamlit_l7/frontend/build/static/js/main.10cbbc1e.chunk.js
streamlit_l7/frontend/build/static/js/main.10cbbc1e.chunk.js.map
streamlit_l7/frontend/build/static/js/main.1ca61b68.chunk.js
streamlit_l7/frontend/build/static/js/main.1ca61b68.chunk.js.map
streamlit_l7/frontend/build/static/js/main.3956aa28.chunk.js
streamlit_l7/frontend/build/static/js/main.3956aa28.chunk.js.map
streamlit_l7/frontend/build/static/js/main.b758a801.chunk.js
streamlit_l7/frontend/build/static/js/main.b758a801.chunk.js.map
streamlit_l7/frontend/build/static/js/main.dd474e40.chunk.js
streamlit_l7/frontend/build/static/js/main.dd474e40.chunk.js.map
streamlit_l7/frontend/build/static/js/runtime-main.a7203729.js
streamlit_l7/frontend/build/static/js/runtime-main.a7203729.js.map
streamlit_l7/frontend/build/static/media/index.272a1409.less
streamlit_l7/frontend/build/static/media/index.4eea6a43.less
streamlit_l7/frontend/build/static/media/index.61564325.less
streamlit_l7/frontend/build/static/media/index.66ba0ced.less
streamlit_l7/frontend/build/static/media/index.84f32f1d.less
streamlit_l7/frontend/build/static/media/index.bdf24db4.less
streamlit_l7/frontend/build/static/media/index.d2e8b1c6.less
streamlit_l7/frontend/build/static/media/index.f0b2cfb9.less
streamlit_l7/frontend/build/static/media/index.fde67ce7.less
streamlit_l7-0.1.6.dist-info/LICENSE
streamlit_l7-0.1.6.dist-info/METADATA
streamlit_l7-0.1.6.dist-info/WHEEL
streamlit_l7-0.1.6.dist-info/top_level.txt
streamlit_l7-0.1.6.dist-info/RECORD
